{
  "api": {
    "kakeiboapi": {
      "service": "AppSync",
      "providerPlugin": "awscloudformation",
      "dependsOn": [
        {
          "category": "auth",
          "resourceName": "kakeibo21f6a44b",
          "attributes": [
            "UserPoolId"
          ]
        }
      ],
      "output": {
        "authConfig": {
          "defaultAuthentication": {
            "authenticationType": "AMAZON_COGNITO_USER_POOLS",
            "userPoolConfig": {
              "userPoolId": "authkakeibo21f6a44b"
            }
          },
          "additionalAuthenticationProviders": []
        }
      }
    }
  },
  "auth": {
    "kakeibo21f6a44b": {
      "service": "Cognito",
      "providerPlugin": "awscloudformation",
      "dependsOn": [],
      "customAuth": false,
      "frontendAuthConfig": {
        "socialProviders": [],
        "usernameAttributes": [],
        "signupAttributes": [
          "EMAIL"
        ],
        "passwordProtectionSettings": {
          "passwordPolicyMinLength": 8,
          "passwordPolicyCharacters": []
        },
        "mfaConfiguration": "OFF",
        "mfaTypes": [
          "SMS"
        ],
        "verificationMechanisms": [
          "EMAIL"
        ]
      }
    }
  }
}